heaptree/__init__.py
heaptree/cli.py
heaptree/client.py
heaptree/enums.py
heaptree/exceptions.py
heaptree/response_wrappers.py
htsdk-0.1.0b12.dist-info/licenses/LICENSE
htsdk-0.1.0b12.dist-info/METADATA
htsdk-0.1.0b12.dist-info/WHEEL
htsdk-0.1.0b12.dist-info/entry_points.txt
htsdk-0.1.0b12.dist-info/top_level.txt
htsdk-0.1.0b12.dist-info/RECORD
