Metadata-Version: 2.4
Name: htsdk
Version: 0.1.0b12
Summary: Heaptree | Launch Virtual Machines With One Line of Code
Author-email: heaptree <heaptreehq@gmail.com>
License-Expression: MIT
Project-URL: Homepage, https://heaptree.com
Classifier: Intended Audience :: Developers
Classifier: Programming Language :: Python :: 3
Classifier: Programming Language :: Python :: 3.9
Classifier: Programming Language :: Python :: 3.10
Classifier: Programming Language :: Python :: 3.11
Classifier: Programming Language :: Python :: 3.12
Classifier: Programming Language :: Python :: 3.13
Classifier: Operating System :: OS Independent
Requires-Python: <4.0,>=3.9
License-File: LICENSE
Requires-Dist: requests>=2.25.1
Dynamic: license-file
